moving_stars/__init__.py
moving_stars/__main__.py
moving_stars/cli.py
moving_stars/clients.py
moving_stars/mapping.py
moving_stars/utils.py
moving_stars-0.1.0.dist-info/METADATA
moving_stars-0.1.0.dist-info/RECORD
moving_stars-0.1.0.dist-info/WHEEL
moving_stars-0.1.0.dist-info/entry_points.txt
moving_stars-0.1.0.dist-info/top_level.txt
