Metadata-Version: 2.1
Name: moving-stars
Version: 0.1.0
Summary: Copy the stars you gave on different Git services.
Home-page: https://gitlab.com/pawamoy/moving-stars
Author: Timothée Mazzucotelli
Author-email: pawamoy@pm.me
License: ISC
Keywords: github,gitlab,#movingtogitlab,stars,git
Platform: UNKNOWN
Classifier: Development Status :: 3 - Alpha
Classifier: Intended Audience :: Developers
Classifier: License :: OSI Approved :: ISC License (ISCL)
Classifier: Operating System :: Unix
Classifier: Programming Language :: Python
Classifier: Programming Language :: Python :: 3
Classifier: Programming Language :: Python :: 3.4
Classifier: Programming Language :: Python :: 3.5
Classifier: Programming Language :: Python :: 3.6
Classifier: Topic :: Utilities
Requires-Dist: requests
Requires-Dist: colorama
Requires-Dist: pytoml
